torchtimer/__init__.py
torchtimer/__version__.py
torchtimer/table.py
torchtimer/timer.py
torchtimer/util.py
torchtimer/plugin/__init__.py
torchtimer/plugin/interactive_legend.py
torchtimer-0.2.0.2.dist-info/LICENSE
torchtimer-0.2.0.2.dist-info/METADATA
torchtimer-0.2.0.2.dist-info/WHEEL
torchtimer-0.2.0.2.dist-info/top_level.txt
torchtimer-0.2.0.2.dist-info/RECORD
