Metadata-Version: 2.1
Name: torchtimer
Version: 0.2.0.2
Summary: A profiling tool for pytorch
Home-page: https://github.com/DeMoriarty/TorchTimer
Download-URL: https://github.com/DeMoriarty/TorchTimer/archive/v_0202.tar.gz
Author: demoriarty
Author-email: sahbanjan@gmail.com
License: MIT
Keywords: pytorch,profiling
Classifier: Development Status :: 3 - Alpha
Classifier: Intended Audience :: Developers
Classifier: Topic :: Software Development :: Build Tools
Classifier: License :: OSI Approved :: MIT License
Classifier: Programming Language :: Python :: 3
Classifier: Programming Language :: Python :: 3.4
Classifier: Programming Language :: Python :: 3.5
Classifier: Programming Language :: Python :: 3.6
Classifier: Programming Language :: Python :: 3.7
Classifier: Programming Language :: Python :: 3.8
Classifier: Programming Language :: Python :: 3.9
Classifier: Programming Language :: Python :: 3.10
License-File: LICENSE
Requires-Dist: numpy
Requires-Dist: torch
Requires-Dist: matplotlib
Requires-Dist: mpld3 (==0.5.7)
